ptyng.py
ptyng-0.3.3.post1.dist-info/DESCRIPTION.rst
ptyng-0.3.3.post1.dist-info/LICENSE.txt
ptyng-0.3.3.post1.dist-info/METADATA
ptyng-0.3.3.post1.dist-info/RECORD
ptyng-0.3.3.post1.dist-info/WHEEL
ptyng-0.3.3.post1.dist-info/metadata.json
ptyng-0.3.3.post1.dist-info/top_level.txt
